sync_fifo.v
 module sync_fifo #(
 parameter DATA_WIDTH = 8,
 parameter DEPTH = 16,
 parameter ADDR_WIDTH = 4
 )(
 input clk,
 input reset,
 input wr_en,
  input rd_en,
  input [DATA_WIDTH-1:0] data_in,
  output reg [DATA_WIDTH-1:0] data_out,
  output reg full,
  output reg empty
 );
  reg [DATA_WIDTH-1:0] mem [0:DEPTH-1];
  reg [ADDR_WIDTH-1:0] wr_ptr = 0, rd_ptr = 0;
  reg [ADDR_WIDTH:0] count = 0;
  always @(posedge clk) begin
    if(reset) begin
      wr_ptr <= 0; rd_ptr <= 0; count <= 0;
      full <= 0; empty <= 1;
    end else begin
      // Write operation
      if(wr_en && !full) begin
        mem[wr_ptr] <= data_in;
        wr_ptr <= wr_ptr + 1;
        count <= count + 1;
      end
      // Read operation
      if(rd_en && !empty) begin
        data_out <= mem[rd_ptr];
        rd_ptr <= rd_ptr + 1;
        count <= count - 1;
      end
      // Update status flags
      full <= (count == DEPTH);
      empty <= (count == 0);
    end
  end
 endmodule

sync_fifo_tb.v
module sync_fifo_tb();

  parameter DATA_WIDTH = 8;
  parameter DEPTH = 16;
  parameter ADDR_WIDTH = 4;

  // Testbench signals
  reg clk;
  reg reset;
  reg wr_en;
  reg rd_en;
  reg [DATA_WIDTH-1:0] data_in;
  wire [DATA_WIDTH-1:0] data_out;
  wire full;
  wire empty;

  // Instantiate the FIFO
  sync_fifo #(
    .DATA_WIDTH(DATA_WIDTH),
    .DEPTH(DEPTH),
    .ADDR_WIDTH(ADDR_WIDTH)
  ) uut (
    .clk(clk),
    .reset(reset),
    .wr_en(wr_en),
    .rd_en(rd_en),
    .data_in(data_in),
    .data_out(data_out),
    .full(full),
    .empty(empty)
  );

  // Clock generation
  always #5 clk = ~clk;  // 100MHz clock

  initial begin

    // VCD dump setup for GTKWave
    $dumpfile("sync_fifo_tb.vcd");
    $dumpvars(0, sync_fifo_tb);
    
    // Initialize signals
    clk = 0;
    reset = 1;
    wr_en = 0;
    rd_en = 0;
    data_in = 0;

    // Reset the FIFO
    #10 reset = 0;

    // Write data to FIFO
    repeat(10) begin
      @(posedge clk);
      wr_en = 1;
      data_in = $random % 256;
    end

    @(posedge clk);
    wr_en = 0;

    // Read data from FIFO
    repeat(10) begin
      @(posedge clk);
      rd_en = 1;
    end

    @(posedge clk);
    rd_en = 0;

    // Final delay and finish
    #20;
    $finish;
  end

endmodule

sync_fifo_tb.vcd
$date
	Sun Jun 08 02:39:31 2025
$end
$version
	Icarus Verilog
$end
$timescale
	1s
$end
$scope module sync_fifo_tb $end
$var wire 1 ! full $end
$var wire 1 " empty $end
$var wire 8 # data_out [7:0] $end
$var parameter 32 $ ADDR_WIDTH $end
$var parameter 32 % DATA_WIDTH $end
$var parameter 32 & DEPTH $end
$var reg 1 ' clk $end
$var reg 8 ( data_in [7:0] $end
$var reg 1 ) rd_en $end
$var reg 1 * reset $end
$var reg 1 + wr_en $end
$scope module uut $end
$var wire 1 ' clk $end
$var wire 8 , data_in [7:0] $end
$var wire 1 ) rd_en $end
$var wire 1 * reset $end
$var wire 1 + wr_en $end
$var parameter 32 - ADDR_WIDTH $end
$var parameter 32 . DATA_WIDTH $end
$var parameter 32 / DEPTH $end
$var reg 5 0 count [4:0] $end
$var reg 8 1 data_out [7:0] $end
$var reg 1 " empty $end
$var reg 1 ! full $end
$var reg 4 2 rd_ptr [3:0] $end
$var reg 4 3 wr_ptr [3:0] $end
$upscope $end
$upscope $end
$enddefinitions $end
$comment Show the parameter values. $end
$dumpall
b10000 /
b1000 .
b100 -
b10000 &
b1000 %
b100 $
$end
#0
$dumpvars
b0 3
b0 2
bx 1
b0 0
b0 ,
0+
1*
0)
b0 (
0'
bx #
x"
x!
$end
#5
1"
0!
1'
#10
0'
0*
#15
b1 0
b1 3
b100100 (
b100100 ,
1+
1'
#20
0'
#25
0"
b10 0
b10 3
b10000001 (
b10000001 ,
1'
#30
0'
#35
b11 0
b11 3
b1001 (
b1001 ,
1'
#40
0'
#45
b100 0
b100 3
b1100011 (
b1100011 ,
1'
#50
0'
#55
b101 0
b101 3
b1101 (
b1101 ,
1'
#60
0'
#65
b110 0
b110 3
b10001101 (
b10001101 ,
1'
#70
0'
#75
b111 0
b111 3
b1100101 (
b1100101 ,
1'
#80
0'
#85
b1000 0
b1000 3
b10010 (
b10010 ,
1'
#90
0'
#95
b1001 0
b1001 3
b1 (
b1 ,
1'
#100
0'
#105
b1010 0
b1010 3
b1101 (
b1101 ,
1'
#110
0'
#115
0+
1'
#120
0'
#125
1)
1'
#130
0'
#135
b1001 0
b1 2
b100100 #
b100100 1
1'
#140
0'
#145
b1000 0
b10 2
1'
#150
0'
#155
b111 0
b11 2
b1001 #
b1001 1
1'
#160
0'
#165
b110 0
b100 2
1'
#170
0'
#175
b101 0
b101 2
b1101 #
b1101 1
1'
#180
0'
#185
b100 0
b110 2
1'
#190
0'
#195
b11 0
b111 2
b1100101 #
b1100101 1
1'
#200
0'
#205
b10 0
b1000 2
1'
#210
0'
#215
b1 0
b1001 2
b1 #
b1 1
1'
#220
0'
#225
b0 0
b1010 2
0)
1'
#230
0'
#235
1"
1'
